Workbook

Sheet Dashboard
B2: RBI IT EXAMINATION — AUDIT TOOLKIT
B3: Public Sector Bank | Based on RBI Master Directions on IT Governance (2023), Cyber Security Framework, DPDP Act 2023
B4: Version 1.0 | Covers: IT Governance, Infrastructure, Cybersecurity, BCP/DR, IS Audit, Outsourcing, Change, Data, Digital Banking, HR Security, Fraud Risk
B7: Domain | C7: Sheet | D7: Total Controls | E7: Compliant | F7: Partial | G7: Non-Compliant | H7: N/A | I7: Score %
B8: IT Governance | C8: IT Governance | D8: 22 | E8: =COUNTIF('IT Governance'!J3:J24,"Compliant") -> 0 | F8: =COUNTIF('IT Governance'!J3:J24,"Partial") -> 0 | G8: =COUNTIF('IT Governance'!J3:J24,"Non-Compliant") -> 0 | H8: =COUNTIF('IT Governance'!J3:J24,"N/A") -> 0 | I8: =IFERROR(E8/(D8-H8),0) -> 0
B9: IT Infrastructure | C9: IT Infrastructure | D9: 23 | E9: =COUNTIF('IT Infrastructure'!J3:J25,"Compliant") -> 0 | F9: =COUNTIF('IT Infrastructure'!J3:J25,"Partial") -> 0 | G9: =COUNTIF('IT Infrastructure'!J3:J25,"Non-Compliant") -> 0 | H9: =COUNTIF('IT Infrastructure'!J3:J25,"N/A") -> 0 | I9: =IFERROR(E9/(D9-H9),0) -> 0
B10: Cybersecurity | C10: Cybersecurity | D10: 31 | E10: =COUNTIF(Cybersecurity!J3:J33,"Compliant") -> 0 | F10: =COUNTIF(Cybersecurity!J3:J33,"Partial") -> 0 | G10: =COUNTIF(Cybersecurity!J3:J33,"Non-Compliant") -> 0 | H10: =COUNTIF(Cybersecurity!J3:J33,"N/A") -> 0 | I10: =IFERROR(E10/(D10-H10),0) -> 0
B11: BCP & DR | C11: BCP&DR | D11: 18 | E11: =COUNTIF('BCP&DR'!J3:J20,"Compliant") -> 0 | F11: =COUNTIF('BCP&DR'!J3:J20,"Partial") -> 0 | G11: =COUNTIF('BCP&DR'!J3:J20,"Non-Compliant") -> 0 | H11: =COUNTIF('BCP&DR'!J3:J20,"N/A") -> 0 | I11: =IFERROR(E11/(D11-H11),0) -> 0
B12: IS Audit | C12: IS Audit | D12: 16 | E12: =COUNTIF('IS Audit'!J3:J18,"Compliant") -> 0 | F12: =COUNTIF('IS Audit'!J3:J18,"Partial") -> 0 | G12: =COUNTIF('IS Audit'!J3:J18,"Non-Compliant") -> 0 | H12: =COUNTIF('IS Audit'!J3:J18,"N/A") -> 0 | I12: =IFERROR(E12/(D12-H12),0) -> 0
B13: IT Outsourcing | C13: IT Outsourcing | D13: 17 | E13: =COUNTIF('IT Outsourcing'!J3:J19,"Compliant") -> 0 | F13: =COUNTIF('IT Outsourcing'!J3:J19,"Partial") -> 0 | G13: =COUNTIF('IT Outsourcing'!J3:J19,"Non-Compliant") -> 0 | H13: =COUNTIF('IT Outsourcing'!J3:J19,"N/A") -> 0 | I13: =IFERROR(E13/(D13-H13),0) -> 0
B14: Change & SDLC | C14: Change&SDLC | D14: 15 | E14: =COUNTIF('Change&SDLC'!J3:J17,"Compliant") -> 0 | F14: =COUNTIF('Change&SDLC'!J3:J17,"Partial") -> 0 | G14: =COUNTIF('Change&SDLC'!J3:J17,"Non-Compliant") -> 0 | H14: =COUNTIF('Change&SDLC'!J3:J17,"N/A") -> 0 | I14: =IFERROR(E14/(D14-H14),0) -> 0
B15: Data Management | C15: Data Management | D15: 16 | E15: =COUNTIF('Data Management'!J3:J18,"Compliant") -> 0 | F15: =COUNTIF('Data Management'!J3:J18,"Partial") -> 0 | G15: =COUNTIF('Data Management'!J3:J18,"Non-Compliant") -> 0 | H15: =COUNTIF('Data Management'!J3:J18,"N/A") -> 0 | I15: =IFERROR(E15/(D15-H15),0) -> 0
B16: Digital Banking & Payments | C16: Digital Banking&Payments | D16: 15 | E16: =COUNTIF('Digital Banking&Payments'!J3:J17,"Compliant") -> 0 | F16: =COUNTIF('Digital Banking&Payments'!J3:J17,"Partial") -> 0 | G16: =COUNTIF('Digital Banking&Payments'!J3:J17,"Non-Compliant") -> 0 | H16: =COUNTIF('Digital Banking&Payments'!J3:J17,"N/A") -> 0 | I16: =IFERROR(E16/(D16-H16),0) -> 0
B17: HR & Physical Security | C17: HR&Physical Security | D17: 10 | E17: =COUNTIF('HR&Physical Security'!J3:J12,"Compliant") -> 0 | F17: =COUNTIF('HR&Physical Security'!J3:J12,"Partial") -> 0 | G17: =COUNTIF('HR&Physical Security'!J3:J12,"Non-Compliant") -> 0 | H17: =COUNTIF('HR&Physical Security'!J3:J12,"N/A") -> 0 | I17: =IFERROR(E17/(D17-H17),0) -> 0
B18: Fraud Risk & Resilience | C18: Fraud Risk&Resilience | D18: 10 | E18: =COUNTIF('Fraud Risk&Resilience'!J3:J12,"Compliant") -> 0 | F18: =COUNTIF('Fraud Risk&Resilience'!J3:J12,"Partial") -> 0 | G18: =COUNTIF('Fraud Risk&Resilience'!J3:J12,"Non-Compliant") -> 0 | H18: =COUNTIF('Fraud Risk&Resilience'!J3:J12,"N/A") -> 0 | I18: =IFERROR(E18/(D18-H18),0) -> 0
B19: TOTAL | D19: =SUM(D8:D18) -> 193 | E19: =SUM(E8:E18) -> 0 | F19: =SUM(F8:F18) -> 0 | G19: =SUM(G8:G18) -> 0 | H19: =SUM(H8:H18) -> 0 | I19: =IFERROR(E19/(D19-H19),0) -> 0
B22: HOW TO USE THIS TOOLKIT
B23: Step 1 | C23: Navigate to each domain sheet (tabs at bottom) and review each control
B24: Step 2 | C24: For each control, select the Compliance Status from the dropdown in column J
B25: Step 3 | C25: Enter your Observations in column K, Evidence Reference in column M, and Auditor Name/Date in columns N-O
B26: Step 4 | C26: Enter Management Response in column P and Target Closure Date in column Q
B27: Step 5 | C27: The Dashboard auto-calculates scores as you update status in each sheet
B28: Step 6 | C28: Use the Audit Rating column (column R) to assign Satisfactory / Needs Improvement / Unsatisfactory
B29: Note | C29: Risk levels: Critical = Regulatory breach risk | High = Significant control gap | Medium = Moderate risk | Low = Minor risk

Sheet IT Governance
A1: RBI IT Examination — IT Governance
A2: Ctrl ID | B2: Domain | C2: Sub-domain | D2: Control Statement / Audit Question | E2: RBI Reference | F2: Risk Level | G2: Control Type | H2: Frequency | I2: Evidence Required | J2: Compliance Status | K2: Auditor Observations | L2: Evidence Reference / Document | M2: Auditor Name | N2: Audit Date | O2: Management Response | P2: Target Closure Date | Q2: Audit Rating | R2: Remarks
A3: GOV-001 | B3: IT Governance | C3: IT Strategy & Board Oversight | D3: Is an IT Strategy Committee (ITSC) constituted at Board level with defined ToR, meeting at least 4 times/year, and documented minutes maintained? | E3: RBI MD IT §3.1 (2023) | F3: Critical | G3: Detective | H3: Quarterly | I3: ITSC minutes, ToR document, Board resolution | J3: Not Tested
A4: GOV-002 | B4: IT Governance | C4: IT Strategy & Board Oversight | D4: Is a Board-approved IT Strategy document in place, aligned with business strategy, reviewed every 3 years or on major business change? | E4: RBI MD IT §3.2 (2023) | F4: High | G4: Preventive | H4: Annual | I4: Board-approved IT strategy, review notes | J4: Not Tested
A5: GOV-003 | B5: IT Governance | C5: IT Strategy & Board Oversight | D5: Does the IT strategy cover digital transformation, cloud adoption, cybersecurity roadmap, and emerging technology plans? | E5: RBI MD IT §3.3 (2023) | F5: High | G5: Preventive | H5: Annual | I5: IT strategy document sections | J5: Not Tested
A6: GOV-004 | B6: IT Governance | C6: IT Steering Committee | D6: Is an IT Steering Committee (ISC) at executive level constituted with CIO, CISO, CFO, and business heads as members? | E6: RBI MD IT §3.4 (2023) | F6: High | G6: Detective | H6: Monthly | I6: ISC charter, meeting minutes | J6: Not Tested
A7: GOV-005 | B7: IT Governance | C7: IT Steering Committee | D7: Does the ISC meet at least monthly with formal agenda, documented decisions, and action tracker reviewed? | E7: RBI MD IT §3.5 (2023) | F7: Medium | G7: Detective | H7: Monthly | I7: ISC meeting minutes (last 12 months) | J7: Not Tested
A8: GOV-006 | B8: IT Governance | C8: IT Policy Framework | D8: Is a comprehensive IT policy framework in place covering all critical areas (security, BCP, vendor, change, incident, access, data) approved by Board? | E8: RBI MD IT §4.1 (2023) | F8: Critical | G8: Preventive | H8: Annual | I8: Policy list with approval dates, Board minutes | J8: Not Tested
A9: GOV-007 | B9: IT Governance | C9: IT Policy Framework | D9: Are all IT policies reviewed at least annually, updated for new regulatory requirements and emerging threats, with version control maintained? | E9: RBI MD IT §4.2 (2023) | F9: High | G9: Preventive | H9: Annual | I9: Policy revision history, last review date | J9: Not Tested
A10: GOV-008 | B10: IT Governance | C10: IT Policy Framework | D10: Is there a documented policy exception management process — logging, CISO/CIO approval, time-bound exceptions with auto-expiry, and periodic review? | E10: RBI MD IT §4.3 (2023) | F10: Medium | G10: Detective | H10: Quarterly | I10: Exception register, approval emails, closure records | J10: Not Tested
A11: GOV-009 | B11: IT Governance | C11: IT Organisation | D11: Is a dedicated Chief Information Officer (CIO) appointed with adequate experience (min. 10 years IT), reporting directly to MD&CEO or Board? | E11: RBI MD IT §5.1 (2023) | F11: Critical | G11: Preventive | H11: Annual | I11: CIO appointment letter, org chart, reporting line | J11: Not Tested
A12: GOV-010 | B12: IT Governance | C12: IT Organisation | D12: Is a Chief Information Security Officer (CISO) appointed at DGM/GM level or above, independent of IT operations, with direct access to Board/ACB? | E12: RBI MD IT §5.2 (2023) | F12: Critical | G12: Preventive | H12: Annual | I12: CISO appointment, independence evidence, ACB reporting | J12: Not Tested
A13: GOV-011 | B13: IT Governance | C13: IT Organisation | D13: Are roles and responsibilities for IT governance clearly documented in RACI/RASCI matrices, communicated, and signed off by role holders? | E13: RBI MD IT §5.3 (2023) | F13: Medium | G13: Preventive | H13: Annual | I13: RACI matrix, role acceptance emails/records | J13: Not Tested
A14: GOV-012 | B14: IT Governance | C14: IT Organisation | D14: Is there a dedicated IT Risk Management function separate from IT operations with qualified staff and reporting to CRO? | E14: RBI MD IT §5.4 (2023) | F14: High | G14: Preventive | H14: Annual | I14: IT Risk function org chart, CRO reporting evidence | J14: Not Tested
... A24: GOV-022 | B24: IT Governance | C24: Regulatory Reporting | D24: Is a regulatory change management process in place to track new RBI/NPCI/IDRBT circulars and implement compliance within prescribed timelines? | E24: RBI MD IT §8.3 (2023) | F24: High | G24: Preventive | H24: Monthly | I24: Circular tracker, implementation evidence | J24: Not Tested

Sheet IT Infrastructure
A1: RBI IT Examination — IT Infrastructure
A2: Ctrl ID | B2: Domain | C2: Sub-domain | D2: Control Statement / Audit Question | E2: RBI Reference | F2: Risk Level | G2: Control Type | H2: Frequency | I2: Evidence Required | J2: Compliance Status | K2: Auditor Observations | L2: Evidence Reference / Document | M2: Auditor Name | N2: Audit Date | O2: Management Response | P2: Target Closure Date | Q2: Audit Rating | R2: Remarks
A3: INF-001 | B3: IT Infrastructure | C3: Data Centre — Physical | D3: Is the primary data centre physically secured with multi-factor biometric access (card + biometric), 24x7 CCTV coverage with 90-day minimum retention? | E3: RBI MD IT §9.1 (2023) | F3: High | G3: Preventive | H3: Semi-Annual | I3: Access control logs, CCTV policy, retention proof | J3: Not Tested
A4: INF-002 | B4: IT Infrastructure | C4: Data Centre — Physical | D4: Are environmental controls in place in DC — fire suppression (FM200/VESDA), UPS, DG sets with auto-failover, precision AC, and leakage detection? | E4: RBI MD IT §9.2 (2023) | F4: High | G4: Preventive | H4: Semi-Annual | I4: Environmental monitoring reports, maintenance records | J4: Not Tested
A5: INF-003 | B5: IT Infrastructure | C5: Data Centre — Physical | D5: Is access to data centre restricted to authorised personnel only with visitor log maintenance and escort policy? | E5: RBI MD IT §9.3 (2023) | F5: High | G5: Preventive | H5: Quarterly | I5: Visitor logs, access authorisation list | J5: Not Tested
A6: INF-004 | B6: IT Infrastructure | C6: DR Site | D6: Is a Disaster Recovery (DR) site established in a geographically separate location (different seismic zone), meeting Tier 3 or above standards? | E6: RBI MD IT §10.1 (2023) | F6: Critical | G6: Preventive | H6: Annual | I6: DR site certificate, seismic zone documentation | J6: Not Tested
A7: INF-005 | B7: IT Infrastructure | C7: DR Site | D7: Is DR site connected to primary DC via diverse network paths (dual MPLS/leased lines with different ISPs) with tested failover capability? | E7: RBI MD IT §10.2 (2023) | F7: Critical | G7: Preventive | H7: Semi-Annual | I7: Network topology, ISP diversity evidence, failover test results | J7: Not Tested
A8: INF-006 | B8: IT Infrastructure | C8: Network Architecture | D8: Is a documented, up-to-date (within 6 months) network architecture diagram in place showing all segments, devices, and data flows? | E8: RBI MD IT §11.1 (2023) | F8: Medium | G8: Preventive | H8: Semi-Annual | I8: Network architecture diagram with version/date | J8: Not Tested
A9: INF-007 | B9: IT Infrastructure | C9: Network Architecture | D9: Is network segmentation implemented with separate DMZ, internal, external, and management zones; inter-zone traffic controlled by NGFW with explicit allow rules? | E9: RBI MD IT §11.2 (2023) | F9: High | G9: Preventive | H9: Annual | I9: Firewall zone diagram, rule review evidence | J9: Not Tested
A10: INF-008 | B10: IT Infrastructure | C10: Network Architecture | D10: Are firewall rules reviewed at least every 6 months with justification, owner, and expiry for each rule; unused/any-any rules removed? | E10: RBI MD IT §11.3 (2023) | F10: High | G10: Detective | H10: Semi-Annual | I10: Firewall rule review reports, cleanup evidence | J10: Not Tested
A11: INF-009 | B11: IT Infrastructure | C11: Network Architecture | D11: Are all inter-branch communications encrypted using SSL/TLS 1.2+ or MPLS with encryption layer; plain-text protocols (Telnet, FTP) disabled? | E11: RBI MD IT §11.4 (2023) | F11: High | G11: Preventive | H11: Annual | I11: Protocol scan reports, encryption evidence | J11: Not Tested
A12: INF-010 | B12: IT Infrastructure | C12: Network Devices | D12: Is a formal patch management process in place for all network devices (routers, switches, firewalls) with SLA: Critical 7 days, High 30 days? | E12: RBI MD IT §11.5 (2023) | F12: High | G12: Preventive | H12: Monthly | I12: Patch management reports, vulnerability status | J12: Not Tested
A13: INF-011 | B13: IT Infrastructure | C13: Network Devices | D13: Are default passwords changed on all network devices and hardening standards (CIS benchmarks) applied and verified annually? | E13: RBI Cyber Circular | F13: Critical | G13: Preventive | H13: Annual | I13: Hardening assessment reports, device configuration review | J13: Not Tested
A14: INF-012 | B14: IT Infrastructure | C14: Asset Management | D14: Is a comprehensive IT asset register maintained (hardware, software, licenses, cloud assets) with automated discovery and quarterly reconciliation? | E14: RBI MD IT §12.1 (2023) | F14: Medium | G14: Detective | H14: Quarterly | I14: Asset register, discovery tool reports, reconciliation evidence | J14: Not Tested
... A25: INF-023 | B25: IT Infrastructure | C25: Cloud Infrastructure | D25: Is a cloud security posture management (CSPM) tool implemented for IaaS/PaaS with misconfiguration alerts and compliance dashboards? | E25: RBI MD IT §14.2 (2023) | F25: High | G25: Detective | H25: Monthly | I25: CSPM reports, misconfiguration remediation records | J25: Not Tested

Sheet Cybersecurity
A1: RBI IT Examination — Cybersecurity
A2: Ctrl ID | B2: Domain | C2: Sub-domain | D2: Control Statement / Audit Question | E2: RBI Reference | F2: Risk Level | G2: Control Type | H2: Frequency | I2: Evidence Required | J2: Compliance Status | K2: Auditor Observations | L2: Evidence Reference / Document | M2: Auditor Name | N2: Audit Date | O2: Management Response | P2: Target Closure Date | Q2: Audit Rating | R2: Remarks
A3: CYB-001 | B3: Cybersecurity | C3: Cyber Security Framework | D3: Is a Board-approved Cyber Security Policy in place aligned with RBI Cyber Security Framework (2016) and subsequent circulars (2019, 2021, 2023)? | E3: RBI Cyber Framework 2016 | F3: Critical | G3: Preventive | H3: Annual | I3: Cyber security policy, Board approval minutes | J3: Not Tested
A4: CYB-002 | B4: Cybersecurity | C4: Cyber Security Framework | D4: Has the bank performed a formal cyber risk assessment (threat modelling, asset criticality, threat-actor profiling) in the last 12 months? | E4: RBI Cyber §3.1 | F4: High | G4: Detective | H4: Annual | I4: Cyber risk assessment report, methodology, sign-off | J4: Not Tested
A5: CYB-003 | B5: Cybersecurity | C5: SOC & SIEM | D5: Is a Security Operations Centre (SOC) established — in-house or managed — providing 24x7x365 monitoring with documented escalation matrix? | E5: RBI Cyber §4.1 | F5: Critical | G5: Detective | H5: Continuous | I5: SOC SLA/contract, escalation matrix, staffing evidence | J5: Not Tested
A6: CYB-004 | B6: Cybersecurity | C6: SOC & SIEM | D6: Is a SIEM solution deployed with coverage of all critical assets (CBS, payment gateways, internet banking, email, AD, firewalls, servers)? | E6: RBI Cyber §4.2 | F6: Critical | G6: Detective | H6: Continuous | I6: SIEM coverage matrix, log source list | J6: Not Tested
A7: CYB-005 | B7: Cybersecurity | C7: SOC & SIEM | D7: Are SIEM use cases/correlation rules reviewed and tuned every 6 months with evidence of new threat-based rule additions? | E7: RBI Cyber §4.3 | F7: High | G7: Detective | H7: Semi-Annual | I7: SIEM rule review report, tuning evidence | J7: Not Tested
A8: CYB-006 | B8: Cybersecurity | C8: SOC & SIEM | D8: Is mean-time-to-detect (MTTD) and mean-time-to-respond (MTTR) tracked monthly with targets (MTTD <30 min, MTTR <4 hours for high-severity)? | E8: RBI Cyber §4.4 | F8: High | G8: Detective | H8: Monthly | I8: SOC KPI dashboard, MTTD/MTTR reports | J8: Not Tested
A9: CYB-007 | B9: Cybersecurity | C9: Privileged Access Management | D9: Is PAM solution implemented for all admin/privileged accounts across servers, network devices, applications, and databases? | E9: RBI Cyber §5.1 | F9: Critical | G9: Preventive | H9: Quarterly | I9: PAM tool coverage report, privileged account list | J9: Not Tested
A10: CYB-008 | B10: Cybersecurity | C10: Privileged Access Management | D10: Is just-in-time (JIT) access implemented for privileged accounts with session recording, dual approval, and no shared/generic admin IDs? | E10: RBI Cyber §5.2 | F10: Critical | G10: Preventive | H10: Quarterly | I10: PAM session recordings, approval records, ID audit | J10: Not Tested
A11: CYB-009 | B11: Cybersecurity | C11: Privileged Access Management | D11: Are privileged accounts reviewed quarterly with evidence of removal of stale/unnecessary accounts? | E11: RBI Cyber §5.3 | F11: High | G11: Detective | H11: Quarterly | I11: Privileged account review reports, deprovisioning evidence | J11: Not Tested
A12: CYB-010 | B12: Cybersecurity | C12: Vulnerability Management | D12: Is vulnerability assessment (VA) conducted monthly for critical assets (CBS, payment, internet banking) and quarterly for all other assets? | E12: RBI Cyber §6.1 | F12: High | G12: Detective | H12: Monthly | I12: VA scan reports, remediation tracker | J12: Not Tested
A13: CYB-011 | B13: Cybersecurity | C13: Vulnerability Management | D13: Are vulnerability remediation SLAs enforced: Critical — 7 days, High — 30 days, Medium — 90 days, with CISO exception approval for breaches? | E13: RBI Cyber §6.2 | F13: High | G13: Detective | H13: Monthly | I13: SLA compliance reports, exception approvals | J13: Not Tested
A14: CYB-012 | B14: Cybersecurity | C14: Penetration Testing | D14: Is external/internal penetration testing conducted at least annually by a CERT-In empanelled auditor covering web apps, network, mobile banking, APIs? | E14: RBI Cyber §6.3 | F14: High | G14: Detective | H14: Annual | I14: Pentest reports (last 2 years), CERT-In empanelment certificate | J14: Not Tested
... A33: CYB-031 | B33: Cybersecurity | C33: Cyber Drills | D33: Is the bank participating in IDRBT/RBI sponsored cyber drills (Samuday/CSITE drill) annually with after-action report submitted? | E33: RBI Cyber Circular | F33: Medium | G33: Detective | H33: Annual | I33: Drill participation evidence, after-action report | J33: Not Tested

Sheet BCP&DR
A1: RBI IT Examination — BCP & DR
A2: Ctrl ID | B2: Domain | C2: Sub-domain | D2: Control Statement / Audit Question | E2: RBI Reference | F2: Risk Level | G2: Control Type | H2: Frequency | I2: Evidence Required | J2: Compliance Status | K2: Auditor Observations | L2: Evidence Reference / Document | M2: Auditor Name | N2: Audit Date | O2: Management Response | P2: Target Closure Date | Q2: Audit Rating | R2: Remarks
A3: BCP-001 | B3: BCP & DR | C3: BCP Policy & Framework | D3: Is a Board-approved Business Continuity Policy in place with clear scope, objectives, roles, and review cycle (annual)? | E3: RBI BCP Guideline §3 | F3: Critical | G3: Preventive | H3: Annual | I3: BCP policy, Board approval minutes | J3: Not Tested
A4: BCP-002 | B4: BCP & DR | C4: Business Impact Analysis | D4: Is a Business Impact Analysis (BIA) conducted and updated within the last 12 months identifying critical functions, MTD, RTO, RPO for all systems? | E4: RBI BCP §3.2 | F4: Critical | G4: Detective | H4: Annual | I4: BIA report, critical function list, MTD/RTO/RPO table | J4: Not Tested
A5: BCP-003 | B5: BCP & DR | C5: RTO & RPO | D5: Are RTO and RPO defined for all critical systems, Board-approved, and technically validated through actual DR failover drills? | E5: RBI BCP §4.1 | F5: Critical | G5: Detective | H5: Semi-Annual | I5: RTO/RPO definitions, DR drill results proving achievement | J5: Not Tested
A6: BCP-004 | B6: BCP & DR | C6: RTO & RPO | D6: Is RTO for Tier-1 systems (CBS, RTGS, payment) defined as ≤4 hours and RPO as ≤15 minutes with synchronous replication evidence? | E6: RBI BCP §4.2 | F6: Critical | G6: Preventive | H6: Semi-Annual | I6: System tier classification, replication monitoring evidence | J6: Not Tested
A7: BCP-005 | B7: BCP & DR | C7: DR Drills | D7: Is a full DR drill (complete failover to DR site) conducted at least twice a year with documented test results, gaps identified, and tracked? | E7: RBI BCP §4.3 | F7: Critical | G7: Detective | H7: Semi-Annual | I7: DR drill reports (last 2 drills), gap tracker | J7: Not Tested
A8: BCP-006 | B8: BCP & DR | C8: DR Drills | D8: Are DR drills conducted without prior notice to IT teams (surprise drills) at least once a year to test actual readiness? | E8: RBI BCP §4.4 | F8: High | G8: Detective | H8: Annual | I8: Surprise drill evidence, results, management sign-off | J8: Not Tested
A9: BCP-007 | B9: BCP & DR | C9: DR Drills | D9: Are business teams (not just IT) included in DR drills to test end-to-end business continuity, not just technical recovery? | E9: RBI BCP §4.5 | F9: High | G9: Detective | H9: Annual | I9: Business team participation records in drill reports | J9: Not Tested
A10: BCP-008 | B10: BCP & DR | C10: Backup Management | D10: Are backup procedures defined for all critical data — daily incremental, weekly full — with off-site/cloud storage and encryption in transit and at rest? | E10: RBI BCP §5.1 | F10: High | G10: Preventive | H10: Monthly | I10: Backup policy, encryption evidence, off-site storage proof | J10: Not Tested
A11: BCP-009 | B11: BCP & DR | C11: Backup Management | D11: Is backup restoration tested at least quarterly for all critical applications with success rate tracked and reported? | E11: RBI BCP §5.2 | F11: High | G11: Detective | H11: Quarterly | I11: Restore test reports, success/failure tracking | J11: Not Tested
A12: BCP-010 | B12: BCP & DR | C12: Backup Management | D12: Is backup integrity verified (hash/checksum) and backup media tested for readability at least semi-annually? | E12: RBI BCP §5.3 | F12: High | G12: Detective | H12: Semi-Annual | I12: Integrity check reports, media readability test results | J12: Not Tested
A13: BCP-011 | B13: BCP & DR | C13: Backup Management | D13: Is backup access restricted with MFA, audit logging, and separation from production environment to prevent ransomware impact? | E13: RBI Cyber Circular | F13: Critical | G13: Preventive | H13: Quarterly | I13: Backup access controls evidence, MFA configuration | J13: Not Tested
A14: BCP-012 | B14: BCP & DR | C14: Near-Zero RPO | D14: Is synchronous/near-synchronous replication implemented for CBS, payment systems, and core databases achieving RPO ≤15 minutes? | E14: RBI BCP §5.4 | F14: High | G14: Preventive | H14: Semi-Annual | I14: Replication monitoring evidence, lag reports | J14: Not Tested
... A20: BCP-018 | B20: BCP & DR | C20: Pandemic / Crisis BCP | D20: Is a remote working / pandemic BCP in place tested and updated covering VPN capacity, endpoint security for remote devices, and third-party dependencies? | E20: RBI COVID Circular | F20: Medium | G20: Preventive | H20: Annual | I20: Remote working BCP, VPN capacity evidence, security controls | J20: Not Tested

Sheet IS Audit
A1: RBI IT Examination — IS Audit
A2: Ctrl ID | B2: Domain | C2: Sub-domain | D2: Control Statement / Audit Question | E2: RBI Reference | F2: Risk Level | G2: Control Type | H2: Frequency | I2: Evidence Required | J2: Compliance Status | K2: Auditor Observations | L2: Evidence Reference / Document | M2: Auditor Name | N2: Audit Date | O2: Management Response | P2: Target Closure Date | Q2: Audit Rating | R2: Remarks
A3: ISA-001 | B3: IS Audit | C3: IS Audit Function | D3: Is an IS Audit function established (in-house or co-sourced) with adequate CISA/CISSP qualified resources and independent reporting to ACB? | E3: RBI MD IT §9.1 (2023) | F3: Critical | G3: Detective | H3: Annual | I3: IS Audit charter, staff qualifications, ACB reporting evidence | J3: Not Tested
A4: ISA-002 | B4: IS Audit | C4: IS Audit Function | D4: Is IS Audit function independent of IT operations and information security function with no conflict of interest? | E4: RBI MD IT §9.2 (2023) | F4: Critical | G4: Preventive | H4: Annual | I4: Independence declaration, org chart showing separation | J4: Not Tested
A5: ISA-003 | B5: IS Audit | C5: IS Audit Plan | D5: Is a risk-based IS Audit plan approved by ACB covering all IT systems, critical applications, infrastructure, and outsourced services annually? | E5: RBI MD IT §9.3 (2023) | F5: High | G5: Preventive | H5: Annual | I5: Risk-based audit plan, ACB approval minutes | J5: Not Tested
A6: ISA-004 | B6: IS Audit | C6: IS Audit Plan | D6: Does the IS audit plan cover CBS, internet banking, mobile banking, payment systems (RTGS/NEFT/IMPS/UPI), treasury, and HR systems annually? | E6: RBI MD IT §9.4 (2023) | F6: High | G6: Preventive | H6: Annual | I6: Audit plan with scope coverage matrix | J6: Not Tested
A7: ISA-005 | B7: IS Audit | C7: Audit Execution | D7: Are IS audit reports completed and submitted to ACB within 30 days of fieldwork completion with formal management responses? | E7: RBI MD IT §9.5 (2023) | F7: High | G7: Detective | H7: Per audit | I7: Audit reports, submission dates, ACB presentations | J7: Not Tested
A8: ISA-006 | B8: IS Audit | C8: Finding Management | D8: Are IS audit findings tracked in a centralised action tracker with management responses, due dates, and evidence of closure? | E8: RBI MD IT §9.6 (2023) | F8: High | G8: Detective | H8: Monthly | I8: Action tracker, closure evidence, ageing report | J8: Not Tested
A9: ISA-007 | B9: IS Audit | C9: Finding Management | D9: Is there an escalation process for overdue IS audit findings with CISO/CIO/ACB escalation for items overdue beyond 90 days? | E9: RBI MD IT §9.7 (2023) | F9: High | G9: Detective | H9: Monthly | I9: Escalation records, overdue ageing report | J9: Not Tested
A10: ISA-008 | B10: IS Audit | C10: Finding Management | D10: Is the IS audit finding repeat status tracked (first-time vs. repeat observation) with enhanced monitoring for repeat findings? | E10: RBI MD IT §9.8 (2023) | F10: High | G10: Detective | H10: Annual | I10: Repeat finding analysis, trend report | J10: Not Tested
A11: ISA-009 | B11: IS Audit | C11: Concurrent Audit | D11: Is concurrent/continuous audit implemented for critical transactions (RTGS, CBS high-value entries, treasury deals) with real-time alerts to auditors? | E11: RBI MD IT §10.1 (2023) | F11: High | G11: Detective | H11: Continuous | I11: Concurrent audit system setup, alert sample evidence | J11: Not Tested
A12: ISA-010 | B12: IS Audit | C12: Concurrent Audit | D12: Is CAAT (Computer Assisted Audit Technique) used for large data analytics, exception reports, duplicate detection, and fraud pattern analysis? | E12: RBI MD IT §10.2 (2023) | F12: Medium | G12: Detective | H12: Per audit | I12: CAAT tool evidence, sample exception reports generated | J12: Not Tested
A13: ISA-011 | B13: IS Audit | C13: External IS Audit | D13: Is a system audit of critical IT systems/applications conducted by an external CERT-In empanelled auditor at least every 2 years? | E13: RBI MD IT §11.1 (2023) | F13: Medium | G13: Detective | H13: Biennial | I13: External audit reports, CERT-In empanelment of auditor | J13: Not Tested
A14: ISA-012 | B14: IS Audit | C14: External IS Audit | D14: Is the scope of external IS audit approved by ACB covering CBS, payment systems, internet/mobile banking, and cybersecurity controls? | E14: RBI MD IT §11.2 (2023) | F14: Medium | G14: Preventive | H14: Biennial | I14: Scope approval by ACB, engagement letter | J14: Not Tested
... A18: ISA-016 | B18: IS Audit | C18: Log Management | D18: Are critical event logs (login failures, privileged access, data exports, configuration changes) reviewed daily by SOC/IS audit team? | E18: RBI MD IT §12.2 (2023) | F18: High | G18: Detective | H18: Daily | I18: Log review evidence, SOC daily review records | J18: Not Tested

Sheet IT Outsourcing
A1: RBI IT Examination — IT Outsourcing
A2: Ctrl ID | B2: Domain | C2: Sub-domain | D2: Control Statement / Audit Question | E2: RBI Reference | F2: Risk Level | G2: Control Type | H2: Frequency | I2: Evidence Required | J2: Compliance Status | K2: Auditor Observations | L2: Evidence Reference / Document | M2: Auditor Name | N2: Audit Date | O2: Management Response | P2: Target Closure Date | Q2: Audit Rating | R2: Remarks
A3: OUT-001 | B3: IT Outsourcing | C3: Outsourcing Policy | D3: Is a Board-approved IT Outsourcing Policy in place covering risk assessment, due diligence criteria, contract requirements, monitoring, and exit strategy? | E3: RBI Outsourcing Guideline §3 | F3: High | G3: Preventive | H3: Annual | I3: IT outsourcing policy, Board approval | J3: Not Tested
A4: OUT-002 | B4: IT Outsourcing | C4: Outsourcing Policy | D4: Does the outsourcing policy explicitly prohibit sub-contracting of critical services without bank's prior written approval? | E4: RBI Outsourcing §3.2 | F4: High | G4: Preventive | H4: Annual | I4: Policy sub-contractor clause, contract verification | J4: Not Tested
A5: OUT-003 | B5: IT Outsourcing | C5: Vendor Register | D5: Is a comprehensive register of all outsourced IT services maintained with risk classification (critical/non-critical) and updated quarterly? | E5: RBI Outsourcing §3.3 | F5: High | G5: Detective | H5: Quarterly | I5: Vendor register with criticality classification, last update date | J5: Not Tested
A6: OUT-004 | B6: IT Outsourcing | C6: Due Diligence | D6: Is a formal due diligence process for new vendor onboarding covering financial stability, security posture, regulatory compliance, and sub-contractor assessment? | E6: RBI Outsourcing §4.1 | F6: High | G6: Preventive | H6: Per vendor | I6: Due diligence checklists, assessment reports for new vendors | J6: Not Tested
A7: OUT-005 | B7: IT Outsourcing | C7: Due Diligence | D7: Is annual due diligence/reassessment conducted for all critical IT vendors with updated security questionnaires and on-site visits? | E7: RBI Outsourcing §4.2 | F7: High | G7: Detective | H7: Annual | I7: Annual vendor assessment reports, on-site visit evidence | J7: Not Tested
A8: OUT-006 | B8: IT Outsourcing | C8: Contract Management | D8: Do all critical IT vendor contracts include right-to-audit clauses enabling bank and RBI to audit vendor premises and systems? | E8: RBI Outsourcing §5.1 | F8: Critical | G8: Preventive | H8: Per contract | I8: Contract audit clause verification, sample contracts | J8: Not Tested
A9: OUT-007 | B9: IT Outsourcing | C9: Contract Management | D9: Do contracts include data security requirements, regulatory access provisions, data localisation (within India), incident notification (within 6 hours), and exit clauses? | E9: RBI Outsourcing §5.2 | F9: Critical | G9: Preventive | H9: Per contract | I9: Contract clause checklist verification, sample contracts | J9: Not Tested
A10: OUT-008 | B10: IT Outsourcing | C10: Contract Management | D10: Are SLAs and OLAs defined for all critical IT vendors covering availability (99.9%+), incident response, RTO, and security requirements? | E10: RBI Outsourcing §5.3 | F10: High | G10: Preventive | H10: Annual | I10: SLA/OLA documents, monitoring evidence | J10: Not Tested
A11: OUT-009 | B11: IT Outsourcing | C11: Vendor Performance | D11: Is vendor performance reviewed quarterly with formal scorecards covering SLA adherence, security incidents, and compliance? | E11: RBI Outsourcing §5.4 | F11: High | G11: Detective | H11: Quarterly | I11: Vendor scorecards, performance review meetings minutes | J11: Not Tested
A12: OUT-010 | B12: IT Outsourcing | C12: Vendor Performance | D12: Is there an escalation and penalty mechanism for SLA breaches with evidence of enforcement? | E12: RBI Outsourcing §5.5 | F12: Medium | G12: Detective | H12: Quarterly | I12: SLA breach records, escalation/penalty enforcement evidence | J12: Not Tested
A13: OUT-011 | B13: IT Outsourcing | C13: Concentration Risk | D13: Is a concentration risk assessment conducted for single-vendor dependencies in critical services (CBS, payment, cloud) with mitigation plans? | E13: RBI Outsourcing §6.1 | F13: High | G13: Detective | H13: Annual | I13: Concentration risk assessment, mitigation plans | J13: Not Tested
A14: OUT-012 | B14: IT Outsourcing | C14: Exit Management | D14: Is there a documented exit management plan (transition/termination) for all critical vendors covering data retrieval, knowledge transfer, and continuity? | E14: RBI Outsourcing §6.2 | F14: Medium | G14: Preventive | H14: Annual | I14: Exit management plans, sample data retrieval test evidence | J14: Not Tested
... A19: OUT-017 | B19: IT Outsourcing | C19: Vendor Audit | D19: Is the right-to-audit exercised for at least critical CBS/payment vendors once in 3 years with formal audit report? | E19: RBI Outsourcing §7.1 | F19: Medium | G19: Detective | H19: Triennial | I19: Vendor audit reports, findings, management responses | J19: Not Tested

Sheet Change&SDLC
A1: RBI IT Examination — Change & SDLC
A2: Ctrl ID | B2: Domain | C2: Sub-domain | D2: Control Statement / Audit Question | E2: RBI Reference | F2: Risk Level | G2: Control Type | H2: Frequency | I2: Evidence Required | J2: Compliance Status | K2: Auditor Observations | L2: Evidence Reference / Document | M2: Auditor Name | N2: Audit Date | O2: Management Response | P2: Target Closure Date | Q2: Audit Rating | R2: Remarks
A3: CHG-001 | B3: Change & SDLC | C3: Change Policy | D3: Is a formal Change Management Policy and process in place covering standard, normal, emergency changes with approval matrix and rollback requirements? | E3: RBI MD IT §12.1 (2023) | F3: High | G3: Preventive | H3: Annual | I3: Change management policy, approval matrix document | J3: Not Tested
A4: CHG-002 | B4: Change & SDLC | C4: Change Advisory Board | D4: Is a Change Advisory Board (CAB) constituted with IT, business, security, and risk function representation for change approval? | E4: RBI MD IT §12.2 (2023) | F4: Medium | G4: Preventive | H4: Annual | I4: CAB charter, membership list, meeting evidence | J4: Not Tested
A5: CHG-003 | B5: Change & SDLC | C5: Change Advisory Board | D5: Does the CAB review all significant/major changes before approval with mandatory security and risk sign-off for changes to critical systems? | E5: RBI MD IT §12.3 (2023) | F5: High | G5: Preventive | H5: Monthly | I5: CAB meeting minutes, approval records for critical changes | J5: Not Tested
A6: CHG-004 | B6: Change & SDLC | C6: Change Testing | D6: Are all production changes tested in a separate non-production environment (UAT/SIT) with test evidence (test cases, results) attached to the change request? | E6: RBI MD IT §12.4 (2023) | F6: High | G6: Preventive | H6: Per change | I6: Change requests with test evidence, UAT sign-off | J6: Not Tested
A7: CHG-005 | B7: Change & SDLC | C7: Change Testing | D7: Is security testing (SAST/DAST) mandatory for all changes to internet-facing and critical banking applications before production deployment? | E7: RBI MD IT §12.5 (2023) | F7: High | G7: Preventive | H7: Per change | I7: Security test reports linked to change requests | J7: Not Tested
A8: CHG-006 | B8: Change & SDLC | C8: Rollback Plan | D8: Is there a documented rollback plan for all significant changes with clearly defined decision point, rollback procedure, and post-rollback validation? | E8: RBI MD IT §12.6 (2023) | F8: High | G8: Preventive | H8: Per change | I8: Rollback plan in change requests, sample rollback tests | J8: Not Tested
A9: CHG-007 | B9: Change & SDLC | C9: Emergency Change | D9: Is there a defined Emergency Change (EC) process with post-implementation review within 48 hours and retrospective CAB approval? | E9: RBI MD IT §12.7 (2023) | F9: High | G9: Preventive | H9: Per EC | I9: Emergency change process doc, post-implementation review records | J9: Not Tested
A10: CHG-008 | B10: Change & SDLC | C10: Change Metrics | D10: Are change success rate, failed changes, and emergency change ratio tracked monthly and reported to ISC with trend analysis? | E10: RBI MD IT §12.8 (2023) | F10: Medium | G10: Detective | H10: Monthly | I10: Change KPI dashboard, ISC reports | J10: Not Tested
A11: CHG-009 | B11: Change & SDLC | C11: Secure SDLC | D11: Is a Secure SDLC (SSDLC) policy mandating security requirements gathering, threat modelling, SAST/DAST, and security sign-off before production release? | E11: RBI MD IT §13.1 (2023) | F11: High | G11: Preventive | H11: Annual | I11: SSDLC policy, security gates checklist, sample compliance | J11: Not Tested
A12: CHG-010 | B12: Change & SDLC | C12: Application Security | D12: Are SAST (static analysis) and DAST (dynamic analysis) tools integrated in CI/CD pipeline for all critical banking application deployments? | E12: RBI MD IT §13.2 (2023) | F12: High | G12: Preventive | H12: Per release | I12: SAST/DAST tool reports linked to CI/CD pipeline | J12: Not Tested
A13: CHG-011 | B13: Change & SDLC | C13: Application Security | D13: Is source code security review (manual or automated) conducted for all in-house developed and significantly modified banking applications? | E13: RBI MD IT §13.3 (2023) | F13: Medium | G13: Preventive | H13: Per release | I13: Code review reports, tool reports, findings | J13: Not Tested
A14: CHG-012 | B14: Change & SDLC | C14: Application Security | D14: Is third-party/open source component analysis (SCA) conducted to identify vulnerable libraries before production deployment? | E14: RBI MD IT §13.4 (2023) | F14: High | G14: Preventive | H14: Per release | I14: SCA scan reports, vulnerable component remediation | J14: Not Tested
... A17: CHG-015 | B17: Change & SDLC | C17: Environment Segregation | D17: Is production data prohibited from use in non-production environments; masked/synthetic data used for testing? | E17: RBI MD IT §13.7 (2023) | F17: Critical | G17: Preventive | H17: Quarterly | I17: Data masking evidence for non-prod, test data policy | J17: Not Tested

Sheet Data Management
A1: RBI IT Examination — Data Management
A2: Ctrl ID | B2: Domain | C2: Sub-domain | D2: Control Statement / Audit Question | E2: RBI Reference | F2: Risk Level | G2: Control Type | H2: Frequency | I2: Evidence Required | J2: Compliance Status | K2: Auditor Observations | L2: Evidence Reference / Document | M2: Auditor Name | N2: Audit Date | O2: Management Response | P2: Target Closure Date | Q2: Audit Rating | R2: Remarks
A3: DAT-001 | B3: Data Management | C3: Data Governance | D3: Is a Data Governance Framework (DGF) in place with a Data Governance Committee (DGC), data owners, and stewards identified for all critical data domains? | E3: RBI DGF Circular | F3: High | G3: Preventive | H3: Annual | I3: DGF document, DGC constitution, data owner assignments | J3: Not Tested
A4: DAT-002 | B4: Data Management | C4: Data Governance | D4: Is a Business Glossary / Data Dictionary maintained for all critical data elements with definitions, owners, and quality rules? | E4: RBI DGF §3.2 | F4: Medium | G4: Preventive | H4: Annual | I4: Business glossary, data dictionary entries | J4: Not Tested
A5: DAT-003 | B5: Data Management | C5: Data Classification | D5: Is a data classification policy in place (public, internal, confidential, sensitive/restricted) with defined handling, storage, and transmission requirements? | E5: RBI DGF §4.1 | F5: High | G5: Preventive | H5: Annual | I5: Data classification policy, classification matrix | J5: Not Tested
A6: DAT-004 | B6: Data Management | C6: Data Classification | D6: Is all customer data (PAN, Aadhaar, account number, mobile, KYC) identified, tagged, and classified as 'Sensitive' with appropriate controls? | E6: RBI DGF §4.2 | F6: Critical | G6: Preventive | H6: Annual | I6: Data classification inventory, sensitive data register | J6: Not Tested
A7: DAT-005 | B7: Data Management | C7: Data Masking | D7: Is sensitive customer data (PAN, Aadhaar, account details, mobile numbers) masked/tokenised in all non-production environments? | E7: RBI DGF §4.3 | F7: Critical | G7: Preventive | H7: Quarterly | I7: Data masking evidence in non-prod, masking tool configuration | J7: Not Tested
A8: DAT-006 | B8: Data Management | C8: Data Quality | D8: Is a Data Quality framework with defined DQ metrics (completeness, accuracy, consistency, timeliness), exception reporting, and remediation tracking implemented? | E8: RBI DGF §4.4 | F8: Medium | G8: Detective | H8: Monthly | I8: DQ metrics dashboard, exception reports, remediation evidence | J8: Not Tested
A9: DAT-007 | B9: Data Management | C9: Data Localisation | D9: Is all payment system data (transaction, settlement, customer PII for payments) stored exclusively within India per RBI April 2018 circular? | E9: RBI Payment Data Apr 2018 | F9: Critical | G9: Preventive | H9: Annual | I9: Data flow diagrams, storage location audit, CSP certificates | J9: Not Tested
A10: DAT-008 | B10: Data Management | C10: Data Localisation | D10: Are all third-party payment data processors/fintech partners compliant with data localisation requirements with contractual and technical evidence? | E10: RBI Payment Data Apr 2018 | F10: Critical | G10: Preventive | H10: Annual | I10: Partner compliance certificates, data audit reports | J10: Not Tested
A11: DAT-009 | B11: Data Management | C11: Data Retention | D11: Is a data retention and deletion policy in place aligned with regulatory timelines (financial records: min. 8 years per RBI) and automated enforcement? | E11: RBI MD IT §14.1 (2023) | F11: High | G11: Preventive | H11: Annual | I11: Data retention policy, automated deletion evidence, archival logs | J11: Not Tested
A12: DAT-010 | B12: Data Management | C12: Data Retention | D12: Is disposal of physical and electronic media (HDDs, tapes) conducted through certified data destruction with certificates maintained? | E12: RBI MD IT §14.2 (2023) | F12: High | G12: Preventive | H12: Annual | I12: Media destruction certificates, vendor empanelment | J12: Not Tested
A13: DAT-011 | B13: Data Management | C13: DPDP Act Compliance | D13: Is a DPDP Act 2023 compliance programme in place with a designated Data Protection Officer (DPO), consent management, and data principal rights handling? | E13: DPDP Act 2023 §8, §10 | F13: High | G13: Preventive | H13: Annual | I13: DPO appointment, consent mechanism evidence, rights handling process | J13: Not Tested
A14: DAT-012 | B14: Data Management | C14: DPDP Act Compliance | D14: Is a Privacy Impact Assessment (PIA) conducted for new systems/processes collecting personal data before go-live? | E14: DPDP Act 2023 §4 | F14: Medium | G14: Preventive | H14: Per project | I14: PIA reports for recent projects | J14: Not Tested
... A18: DAT-016 | B18: Data Management | C18: Analytics & AI | D18: For AI/ML models used in credit decisions or fraud detection, is there a model risk management framework covering validation, monitoring, and explainability? | E18: RBI Model Risk Circular | F18: Medium | G18: Detective | H18: Annual | I18: Model risk policy, model validation reports, monitoring dashboards | J18: Not Tested

Sheet Digital Banking&Payments
A1: RBI IT Examination — Digital Banking & Payments
A2: Ctrl ID | B2: Domain | C2: Sub-domain | D2: Control Statement / Audit Question | E2: RBI Reference | F2: Risk Level | G2: Control Type | H2: Frequency | I2: Evidence Required | J2: Compliance Status | K2: Auditor Observations | L2: Evidence Reference / Document | M2: Auditor Name | N2: Audit Date | O2: Management Response | P2: Target Closure Date | Q2: Audit Rating | R2: Remarks
A3: DIG-001 | B3: Digital Banking & Payments | C3: Internet Banking Security | D3: Is internet banking platform secured with HTTPS, TLS 1.2+, valid EV SSL certificate, and HSTS headers? | E3: RBI Internet Banking Guideline | F3: Critical | G3: Preventive | H3: Quarterly | I3: SSL certificate report, TLS configuration scan, header analysis | J3: Not Tested
A4: DIG-002 | B4: Digital Banking & Payments | C4: Internet Banking Security | D4: Is re-authentication enforced for high-value transactions in internet banking (transaction password, OTP, biometric)? | E4: RBI Internet Banking Guideline §4 | F4: Critical | G4: Preventive | H4: Quarterly | I4: Transaction authentication configuration, test evidence | J4: Not Tested
A5: DIG-003 | B5: Digital Banking & Payments | C5: Internet Banking Security | D5: Is session management secure — session timeout (max. 5 minutes idle), single active session, secure cookie attributes (HTTPOnly, Secure, SameSite)? | E5: RBI Internet Banking Guideline §5 | F5: High | G5: Preventive | H5: Annual | I5: Session management configuration review, test evidence | J5: Not Tested
A6: DIG-004 | B6: Digital Banking & Payments | C6: Mobile Banking Security | D6: Is mobile banking app security tested (OWASP Mobile Top 10) at least annually by an external auditor with findings remediated? | E6: RBI Mobile Banking Circular | F6: High | G6: Detective | H6: Annual | I6: Mobile app pentest reports, OWASP coverage, remediation evidence | J6: Not Tested
A7: DIG-005 | B7: Digital Banking & Payments | C7: Mobile Banking Security | D7: Is certificate pinning implemented in mobile banking app to prevent MITM attacks? | E7: RBI Mobile Banking Circular §3 | F7: High | G7: Preventive | H7: Annual | I7: Certificate pinning implementation evidence, pentest confirmation | J7: Not Tested
A8: DIG-006 | B8: Digital Banking & Payments | C8: Mobile Banking Security | D8: Is mobile banking app available on official stores only; fake app monitoring service subscribed with takedown capability? | E8: RBI Mobile Banking Circular §4 | F8: Medium | G8: Detective | H8: Monthly | I8: Fake app monitoring subscription, takedown records | J8: Not Tested
A9: DIG-007 | B9: Digital Banking & Payments | C9: UPI & Payment Security | D9: Is UPI/IMPS/NEFT/RTGS transaction limit set per RBI guidelines with customer-configurable limits and velocity checks? | E9: RBI Payment Guidelines | F9: Critical | G9: Preventive | H9: Annual | I9: Transaction limit configuration, velocity rule evidence | J9: Not Tested
A10: DIG-008 | B10: Digital Banking & Payments | C10: UPI & Payment Security | D10: Are real-time fraud monitoring rules implemented for payment transactions with automatic blocking and SMS/email alert to customer for suspicious transactions? | E10: RBI Fraud Monitoring Circular | F10: Critical | G10: Detective | H10: Continuous | I10: Fraud rule documentation, alert sample, blocking evidence | J10: Not Tested
A11: DIG-009 | B11: Digital Banking & Payments | C11: UPI & Payment Security | D11: Is NPCI's fraud risk management framework implemented with dispute handling SLA met and reporting to NPCI on time? | E11: NPCI FRM Circular | F11: High | G11: Detective | H11: Monthly | I11: NPCI dispute reports, SLA compliance, reporting evidence | J11: Not Tested
A12: DIG-010 | B12: Digital Banking & Payments | C12: ATM Security | D12: Are ATMs protected with physical skimmer/shimmer detection and logical security (hard disk encryption, whitelisting, anti-skimming software)? | E12: RBI ATM Security Circular | F12: Critical | G12: Preventive | H12: Annual | I12: ATM security assessment reports, anti-skimming deployment evidence | J12: Not Tested
A13: DIG-011 | B13: Digital Banking & Payments | C13: ATM Security | D13: Is ATM network (NCN) segregated from bank's corporate network with dedicated VLAN and monitoring? | E13: RBI ATM Security Circular §3 | F13: High | G13: Preventive | H13: Annual | I13: Network segregation evidence, ATM VLAN configuration | J13: Not Tested
A14: DIG-012 | B14: Digital Banking & Payments | C14: Customer Protection | D14: Is a mechanism in place for customers to report fraud/unauthorized transactions 24x7 with zero liability protection as per RBI Customer Protection Circular? | E14: RBI Cust Protection Circular 2017 | F14: Critical | G14: Preventive | H14: Annual | I14: Fraud reporting mechanism, zero liability policy, process evidence | J14: Not Tested
... A17: DIG-015 | B17: Digital Banking & Payments | C17: Fintech & Third-Party | D17: Are all third-party apps integrated via APIs subjected to security assessment and contractual data security obligations before go-live? | E17: RBI Fintech Circular | F17: High | G17: Preventive | H17: Per integration | I17: Third-party security assessment, contract clauses | J17: Not Tested

Sheet HR&Physical Security
A1: RBI IT Examination — HR & Physical Security
A2: Ctrl ID | B2: Domain | C2: Sub-domain | D2: Control Statement / Audit Question | E2: RBI Reference | F2: Risk Level | G2: Control Type | H2: Frequency | I2: Evidence Required | J2: Compliance Status | K2: Auditor Observations | L2: Evidence Reference / Document | M2: Auditor Name | N2: Audit Date | O2: Management Response | P2: Target Closure Date | Q2: Audit Rating | R2: Remarks
A3: HRS-001 | B3: HR & Physical Security | C3: Background Verification | D3: Is background verification (BGV) conducted for all new employees including IT/security staff covering criminal, education, employment, and financial checks? | E3: RBI MD IT §15.1 (2023) | F3: High | G3: Preventive | H3: Per hire | I3: BGV reports for recent joiners, vendor agreement | J3: Not Tested
A4: HRS-002 | B4: HR & Physical Security | C4: Background Verification | D4: Is periodic re-verification conducted for employees in sensitive roles (IT admin, security, treasury, CBS admin) every 3 years? | E4: RBI MD IT §15.2 (2023) | F4: High | G4: Preventive | H4: Triennial | I4: Re-verification policy, recent re-verification records | J4: Not Tested
A5: HRS-003 | B5: HR & Physical Security | C5: Separation Process | D5: Is a formal IT access revocation process in place ensuring all access (physical and logical) is revoked within 24 hours of employee exit? | E5: RBI MD IT §15.3 (2023) | F5: Critical | G5: Preventive | H5: Monthly | I5: Exit clearance records, access revocation TAT reports | J5: Not Tested
A6: HRS-004 | B6: HR & Physical Security | C6: Separation Process | D6: Is an exit interview/debriefing conducted for IT/security staff covering NDA, IP return, and data handling obligations? | E6: RBI MD IT §15.4 (2023) | F6: Medium | G6: Preventive | H6: Per exit | I6: Exit interview records for IT/security staff | J6: Not Tested
A7: HRS-005 | B7: HR & Physical Security | C7: Insider Threat | D7: Is a User and Entity Behaviour Analytics (UEBA) solution deployed or integrated with SIEM to detect insider threat indicators (bulk downloads, off-hours access)? | E7: RBI Cyber Circular | F7: High | G7: Detective | H7: Continuous | I7: UEBA deployment/SIEM UEBA rule evidence, sample alerts | J7: Not Tested
A8: HRS-006 | B8: HR & Physical Security | C8: Physical Security | D8: Is physical access to critical areas (DC, operations, treasury) controlled by biometric + card with access log review monthly? | E8: RBI MD IT §16.1 (2023) | F8: High | G8: Preventive | H8: Monthly | I8: Physical access logs, review evidence | J8: Not Tested
A9: HRS-007 | B9: HR & Physical Security | C9: Physical Security | D9: Is a clean desk and clear screen policy enforced with periodic compliance checks (unannounced walkthroughs)? | E9: RBI MD IT §16.2 (2023) | F9: Medium | G9: Preventive | H9: Quarterly | I9: Clean desk policy, walkthrough evidence/reports | J9: Not Tested
A10: HRS-008 | B10: HR & Physical Security | C10: Third-Party Personnel | D10: Are contractor/vendor personnel given time-limited, minimal access with NDA signed before access and access revoked immediately on engagement end? | E10: RBI MD IT §16.3 (2023) | F10: High | G10: Preventive | H10: Monthly | I10: Contractor access policy, NDA records, timely revocation evidence | J10: Not Tested
A11: HRS-009 | B11: HR & Physical Security | C11: Security Culture | D11: Is a security culture survey conducted annually to measure employee awareness and satisfaction with security controls? | E11: RBI MD IT §16.4 (2023) | F11: Low | G11: Detective | H11: Annual | I11: Security culture survey results, action plan | J11: Not Tested
A12: HRS-010 | B12: HR & Physical Security | C12: Key Person Risk | D12: Is succession planning in place for critical IT/security roles (CIO, CISO, CBS admin) to manage key person dependency risk? | E12: RBI MD IT §16.5 (2023) | F12: Medium | G12: Preventive | H12: Annual | I12: Succession plan document, cross-training evidence | J12: Not Tested

Sheet Fraud Risk&Resilience
A1: RBI IT Examination — Fraud Risk & Resilience
A2: Ctrl ID | B2: Domain | C2: Sub-domain | D2: Control Statement / Audit Question | E2: RBI Reference | F2: Risk Level | G2: Control Type | H2: Frequency | I2: Evidence Required | J2: Compliance Status | K2: Auditor Observations | L2: Evidence Reference / Document | M2: Auditor Name | N2: Audit Date | O2: Management Response | P2: Target Closure Date | Q2: Audit Rating | R2: Remarks
A3: FRD-001 | B3: Fraud Risk & Resilience | C3: Fraud Monitoring | D3: Is a real-time fraud monitoring system (FMS/FRM) deployed covering all digital channels (internet banking, mobile, UPI, ATM, POS) with 24x7 alerting? | E3: RBI Fraud Monitoring Circular | F3: Critical | G3: Detective | H3: Continuous | I3: FMS deployment evidence, channel coverage, alert samples | J3: Not Tested
A4: FRD-002 | B4: Fraud Risk & Resilience | C4: Fraud Monitoring | D4: Are fraud monitoring rules reviewed and updated at least quarterly based on emerging fraud patterns, threat intelligence, and NPCI/RBI advisories? | E4: RBI Fraud Monitoring §3 | F4: High | G4: Detective | H4: Quarterly | I4: Fraud rule review records, update evidence, approvals | J4: Not Tested
A5: FRD-003 | B5: Fraud Risk & Resilience | C5: Fraud Reporting | D5: Are all fraud incidents reported to RBI (FMR returns) within the prescribed timelines with accurate classification (cyber fraud, social engineering, internal)? | E5: RBI Fraud Reporting Circular | F5: Critical | G5: Detective | H5: Monthly | I5: FMR return submissions, timeliness records | J5: Not Tested
A6: FRD-004 | B6: Fraud Risk & Resilience | C6: Fraud Reporting | D6: Is a fraud incident register maintained with root cause analysis, customer impact, recovery actions, and control improvements tracked? | E6: RBI Fraud Monitoring §4 | F6: High | G6: Detective | H6: Monthly | I6: Fraud register, RCA reports, control improvement evidence | J6: Not Tested
A7: FRD-005 | B7: Fraud Risk & Resilience | C7: Social Engineering | D7: Is a social engineering defence programme in place covering CEO fraud/BEC, vishing, and smishing with controls and customer education? | E7: RBI Cyber Circular | F7: High | G7: Preventive | H7: Annual | I7: Programme documentation, customer advisory samples, staff training | J7: Not Tested
A8: FRD-006 | B8: Fraud Risk & Resilience | C8: Ransomware Resilience | D8: Is a ransomware resilience plan in place covering immutable backups, network isolation procedures, CSIRP activation, and tested recovery? | E8: RBI Cyber Circular | F8: Critical | G8: Preventive | H8: Annual | I8: Ransomware response plan, immutable backup evidence, drill results | J8: Not Tested
A9: FRD-007 | B9: Fraud Risk & Resilience | C9: Supply Chain Security | D9: Is software supply chain security addressed — vendor code signing, integrity verification, SBOM (software bill of materials) for critical applications? | E9: RBI Cyber Circular | F9: High | G9: Preventive | H9: Annual | I9: Code signing evidence, SBOM documentation | J9: Not Tested
A10: FRD-008 | B10: Fraud Risk & Resilience | C10: Zero-Day Response | D10: Is there a process to respond to zero-day vulnerabilities — CERT-In/vendor advisory monitoring, emergency patching protocol, and compensating controls? | E10: RBI Cyber Circular | F10: High | G10: Detective | H10: Per event | I10: Zero-day response process, recent advisory response evidence | J10: Not Tested
A11: FRD-009 | B11: Fraud Risk & Resilience | C11: Cyber Insurance | D11: Has the bank evaluated or obtained cyber insurance coverage commensurate with cyber risk exposure, covering incident response, ransomware, and liability? | E11: RBI MD IT §17.1 (2023) | F11: Low | G11: Preventive | H11: Annual | I11: Cyber insurance policy or evaluation evidence | J11: Not Tested
A12: FRD-010 | B12: Fraud Risk & Resilience | C12: Technology Obsolescence | D12: Is a formal technology obsolescence risk management programme in place tracking and mitigating risks from legacy/unsupported technologies? | E12: RBI MD IT §17.2 (2023) | F12: High | G12: Preventive | H12: Annual | I12: Technology obsolescence register, mitigation plans, ITSC approval | J12: Not Tested
